codet/__init__.py
codet/cli.py
codet/clog.py
codet/codet.py
codet/dash.py
codet/git_compoent.py
codet-1.0.7.dist-info/licenses/LICENSE
codet-1.0.7.dist-info/METADATA
codet-1.0.7.dist-info/WHEEL
codet-1.0.7.dist-info/entry_points.txt
codet-1.0.7.dist-info/top_level.txt
codet-1.0.7.dist-info/RECORD
