Metadata-Version: 2.4
Name: codet
Version: 1.0.7
Summary: A cross-platform command-line tool for file processing and Git repository analysis with support for commit history tracking, code hotspot detection, and customizable filtering options
Home-page: https://github.com/clemente0731/codet
Author: clemente0620
Author-email: clemente0620@gmail.com
Classifier: Programming Language :: Python :: 3
Classifier: Programming Language :: Python :: 3.6
Classifier: Programming Language :: Python :: 3.7
Classifier: Programming Language :: Python :: 3.8
Classifier: Programming Language :: Python :: 3.9
Classifier: Programming Language :: Python :: 3.10
Classifier: Programming Language :: Python :: 3.11
Classifier: Programming Language :: Python :: 3.12
Classifier: License :: OSI Approved :: MIT License
Classifier: Operating System :: OS Independent
Requires-Python: >=3.6
License-File: LICENSE
Requires-Dist: colorlog>=6.0.0
Requires-Dist: gitpython>=3.1.0
Requires-Dist: typing>=3.7.4
Requires-Dist: prettytable>=3.12.0
Requires-Dist: tqdm>=4.60.0
Requires-Dist: openai>=1.84.0
Requires-Dist: dash>=2.14.0
Requires-Dist: plotly>=5.15.0
Requires-Dist: pandas
Requires-Dist: dash-bootstrap-components
Provides-Extra: dev
Requires-Dist: pytest>=6.0.0; extra == "dev"
Requires-Dist: black>=21.5b2; extra == "dev"
Requires-Dist: isort>=5.9.1; extra == "dev"
Requires-Dist: flake8>=3.9.2; extra == "dev"
Requires-Dist: twine>=3.4.1; extra == "dev"
Dynamic: author
Dynamic: author-email
Dynamic: classifier
Dynamic: description
Dynamic: description-content-type
Dynamic: home-page
Dynamic: license-file
Dynamic: provides-extra
Dynamic: requires-dist
Dynamic: requires-python
Dynamic: summary
